{
	"GLib": {
		"Pkgs"    : ["glib-2.0"],
		"Headers" : ["glib.h", "glib/gstdio.h", "glib-unix.h"],
		"Typedefs": {},
		"Imports" : ["reflect"]
	},
	"GObject": {
		"Pkgs"    : ["gobject-2.0"],
		"Headers" : ["glib-object.h"],
		"Typedefs": {},
		"Imports" : ["container/list"]
	},
	"Gtk" : {
		"Pkgs"    : ["gtk+-3.0", "cairo"],
		"Headers" : ["gtk/gtk.h", "cairo.h"],
		"Typedefs": {
			"CairoRegion": "cairo_region_t",
			"CairoContext": "cairo_t",
			"CairoRectangleInt": "cairo_rectangle_int_t"
		},
		"Imports" : []
	}
}
